python_commander/__init__.py
python_commander/py_commander.py
python_commander/tests/__init__.py
python_commander/tests/test_commander.py
python_commander-0.1.1.dist-info/LICENSE
python_commander-0.1.1.dist-info/METADATA
python_commander-0.1.1.dist-info/WHEEL
python_commander-0.1.1.dist-info/entry_points.txt
python_commander-0.1.1.dist-info/top_level.txt
python_commander-0.1.1.dist-info/RECORD
