Metadata-Version: 2.1
Name: python-commander
Version: 0.1.1
Summary: A spin-off from Django's manager.py
Home-page: https://github.com/Bloodlister/python_commander
Author: Bloodlister
Author-email: AsenJ.Mihaylov@gmail.com
License: MIT
Platform: UNKNOWN
Classifier: Programming Language :: Python :: 3
Classifier: License :: OSI Approved :: MIT License
Classifier: Operating System :: OS Independent
Requires-Dist: pick
